domainsearch/__init__.py
domainsearch/__main__.py
domainsearch/main.py
domainsearch/main_test.py
domainsearch/version.py
domainsearch-1.0.2.dist-info/METADATA
domainsearch-1.0.2.dist-info/WHEEL
domainsearch-1.0.2.dist-info/entry_points.txt
domainsearch-1.0.2.dist-info/top_level.txt
domainsearch-1.0.2.dist-info/RECORD
