Metadata-Version: 2.1
Name: domainsearch
Version: 1.0.2
Summary: Search for available domains using wildcards
Home-page: https://github.com/jeremija/domainsearch
Author: Jerko Steiner
Author-email: jerko.steiner@gmail.com
License: UNKNOWN
Platform: UNKNOWN
Classifier: Programming Language :: Python :: 3 :: Only
Classifier: License :: OSI Approved :: MIT License
Classifier: Operating System :: OS Independent
